qonversion/__init__.py
qonversion/api_requestor.py
qonversion/error.py
qonversion/http_client.py
qonversion/logger.py
qonversion/object_map.py
qonversion/qobject.py
qonversion/response.py
qonversion/utils.py
qonversion/version.py
qonversion/api_resources/__init__.py
qonversion/api_resources/entitlement.py
qonversion/api_resources/error_object.py
qonversion/api_resources/identity.py
qonversion/api_resources/product.py
qonversion/api_resources/purchase.py
qonversion/api_resources/subscription.py
qonversion/api_resources/user.py
qonversion/api_resources/base/__init__.py
qonversion/api_resources/base/api_resource.py
qonversion/api_resources/base/creatable_api_resource.py
qonversion/api_resources/base/retrievable_api_resource.py
qonversion_sdk-0.0.1.dist-info/LICENSE
qonversion_sdk-0.0.1.dist-info/METADATA
qonversion_sdk-0.0.1.dist-info/WHEEL
qonversion_sdk-0.0.1.dist-info/top_level.txt
qonversion_sdk-0.0.1.dist-info/RECORD
