Metadata-Version: 2.1
Name: qonversion-sdk
Version: 0.0.1
Summary: Python bindings for the Qonversion API
Home-page: https://github.com/qonversion/python-sdk
Author: qonversion
Author-email: hi@qonversion.io
License: MIT
Project-URL: Source Code, https://github.com/qonversion/python-sdk
Platform: UNKNOWN
Classifier: Intended Audience :: Developers
Classifier: License :: OSI Approved :: MIT License
Classifier: Operating System :: OS Independent
Classifier: Programming Language :: Python
Classifier: Programming Language :: Python :: 3.6
Classifier: Programming Language :: Python :: 3.7
Classifier: Programming Language :: Python :: 3.8
Classifier: Programming Language :: Python :: 3.9
Classifier: Topic :: Software Development :: Libraries :: Python Modules
Requires-Python: >=3.6
Requires-Dist: requests (>=2.20) ; python_version >= "3.6"
